{
  "appInfo" : {
    "build" : "222.3345.118",
    "buildDate" : "2022-07-26T05:01:21.392Z[UTC]",
    "productCode" : "IC",
    "generated" : "2025-07-08T06:49:34.71707Z",
    "os" : "macOS 15.4.1",
    "runtime" : "JetBrains s.r.o. 17.0.3 17.0.3+7-b469.32"
  },
  "runtimeInfo" : {
    "maxMemory" : 786432000,
    "numberOfProcessors" : 8,
    "maxNumberOfIndexingThreads" : 4,
    "maxSizeOfFileForIntelliSense" : 2560000,
    "maxSizeOfFileForContentLoading" : 20971520
  },
  "projectIndexingHistory" : {
    "projectName" : "doc",
    "times" : {
      "indexingReason" : "On project open",
      "scanningType" : "FULL_ON_PROJECT_OPEN",
      "totalUpdatingTime" : 1140121495,
      "indexingTime" : 32531000,
      "contentLoadingVisibleTime" : 7739190,
      "creatingIteratorsTime" : 5710000,
      "scanFilesTime" : 852293000,
      "pushPropertiesTime" : 55000,
      "indexExtensionsTime" : 0,
      "isAppliedAllValuesSeparately" : true,
      "separateApplyingIndexesVisibleTime" : 1292859,
      "updatingStart" : "2025-07-08T06:49:33.56856Z",
      "updatingEnd" : "2025-07-08T06:49:34.70869Z",
      "totalSuspendedTime" : 0,
      "wasInterrupted" : false
    },
    "fileCount" : {
      "numberOfFileProviders" : 5,
      "numberOfScannedFiles" : 284,
      "numberOfFilesIndexedByInfrastructureExtensionsDuringScan" : 0,
      "numberOfFilesScheduledForIndexingAfterScan" : 1,
      "numberOfFilesIndexedByInfrastructureExtensionsDuringIndexingStage" : 0,
      "numberOfFilesIndexedWithLoadingContent" : 1
    },
    "totalStatsPerFileType" : [ {
      "fileType" : "UNKNOWN",
      "partOfTotalProcessingTime" : {
        "part" : 14282091,
        "total" : 14282091
      },
      "partOfTotalContentLoadingTime" : {
        "part" : 5733898,
        "total" : 5733898
      },
      "totalNumberOfFiles" : 1,
      "totalFilesSize" : 1939,
      "indexingSpeed" : {
        "totalBytes" : 1939,
        "totalTime" : 14282091
      },
      "biggestContributors" : [ {
        "providerName" : "Module 'doc' (doc)",
        "numberOfFiles" : 1,
        "totalFilesSize" : 1939,
        "partOfTotalProcessingTimeOfThisFileType" : {
          "part" : 14282091,
          "total" : 14282091
        }
      } ]
    } ],
    "totalStatsPerIndexer" : [ ],
    "scanningStatistics" : [ {
      "providerName" : "Module 'doc' (doc)",
      "numberOfScannedFiles" : 55,
      "numberOfSkippedFiles" : 0,
      "numberOfFilesForIndexing" : 1,
      "numberOfFilesFullyIndexedByInfrastructureExtensions" : 0,
      "filesFullyIndexedByInfrastructureExtensions" : [ ],
      "statusTime" : 736883909,
      "scanningTime" : 757205099,
      "timeProcessingUpToDateFiles" : 0,
      "timeUpdatingContentLessIndexes" : 433623,
      "timeIndexingWithoutContent" : 12278658,
      "roots" : [ ]
    }, {
      "providerName" : "Indexable set contributor 'com.intellij.javaee.ExternalResourcesRootsProvider@7d15df83' (non-project)",
      "numberOfScannedFiles" : 229,
      "numberOfSkippedFiles" : 4,
      "numberOfFilesForIndexing" : 0,
      "numberOfFilesFullyIndexedByInfrastructureExtensions" : 0,
      "filesFullyIndexedByInfrastructureExtensions" : [ ],
      "statusTime" : 741222418,
      "scanningTime" : 748693186,
      "timeProcessingUpToDateFiles" : 0,
      "timeUpdatingContentLessIndexes" : 2211318,
      "timeIndexingWithoutContent" : 0,
      "roots" : [ ]
    }, {
      "providerName" : "Indexable set contributor 'Scratches & Consoles' (project)",
      "numberOfScannedFiles" : 0,
      "numberOfSkippedFiles" : 0,
      "numberOfFilesForIndexing" : 0,
      "numberOfFilesFullyIndexedByInfrastructureExtensions" : 0,
      "filesFullyIndexedByInfrastructureExtensions" : [ ],
      "statusTime" : 0,
      "scanningTime" : 0,
      "timeProcessingUpToDateFiles" : 0,
      "timeUpdatingContentLessIndexes" : 0,
      "timeIndexingWithoutContent" : 0,
      "roots" : [ ]
    }, {
      "providerName" : "Indexable set contributor 'com.intellij.javaee.ExternalResourcesRootsProvider@7d15df83' (project)",
      "numberOfScannedFiles" : 0,
      "numberOfSkippedFiles" : 0,
      "numberOfFilesForIndexing" : 0,
      "numberOfFilesFullyIndexedByInfrastructureExtensions" : 0,
      "filesFullyIndexedByInfrastructureExtensions" : [ ],
      "statusTime" : 0,
      "scanningTime" : 0,
      "timeProcessingUpToDateFiles" : 0,
      "timeUpdatingContentLessIndexes" : 0,
      "timeIndexingWithoutContent" : 0,
      "roots" : [ ]
    }, {
      "providerName" : "Indexable set contributor 'Scratches & Consoles' (non-project)",
      "numberOfScannedFiles" : 0,
      "numberOfSkippedFiles" : 0,
      "numberOfFilesForIndexing" : 0,
      "numberOfFilesFullyIndexedByInfrastructureExtensions" : 0,
      "filesFullyIndexedByInfrastructureExtensions" : [ ],
      "statusTime" : 0,
      "scanningTime" : 0,
      "timeProcessingUpToDateFiles" : 0,
      "timeUpdatingContentLessIndexes" : 0,
      "timeIndexingWithoutContent" : 0,
      "roots" : [ ]
    } ],
    "fileProviderStatistics" : [ {
      "providerName" : "Module 'doc' (doc)",
      "totalNumberOfIndexedFiles" : 1,
      "totalNumberOfFilesFullyIndexedByExtensions" : 0,
      "totalIndexingVisibleTime" : 19276909,
      "contentLoadingVisibleTime" : 7739190,
      "numberOfTooLargeForIndexingFiles" : 0,
      "slowIndexedFiles" : [ ],
      "filesFullyIndexedByExtensions" : [ ],
      "isAppliedAllValuesSeparately" : true,
      "separateApplyingIndexesVisibleTime" : 1292859
    } ],
    "visibleTimeToAllThreadTimeRatio" : 1.3497259609954873
  }
}