{
  "appInfo" : {
    "build" : "222.3345.118",
    "buildDate" : "2022-07-26T05:01:27.388Z[UTC]",
    "productCode" : "IC",
    "generated" : "2025-07-08T06:36:39.132432Z",
    "os" : "macOS 15.4.1",
    "runtime" : "JetBrains s.r.o. 17.0.3 17.0.3+7-b469.32"
  },
  "runtimeInfo" : {
    "maxMemory" : 786432000,
    "numberOfProcessors" : 8,
    "maxNumberOfIndexingThreads" : 4,
    "maxSizeOfFileForIntelliSense" : 2560000,
    "maxSizeOfFileForContentLoading" : 20971520
  },
  "projectIndexingHistory" : {
    "projectName" : "doc",
    "times" : {
      "indexingReason" : "On project open",
      "scanningType" : "FULL_ON_PROJECT_OPEN",
      "totalUpdatingTime" : 1109650646,
      "indexingTime" : 24560000,
      "contentLoadingVisibleTime" : 7294177,
      "creatingIteratorsTime" : 21097000,
      "scanFilesTime" : 859355000,
      "pushPropertiesTime" : 1216000,
      "indexExtensionsTime" : 0,
      "isAppliedAllValuesSeparately" : true,
      "separateApplyingIndexesVisibleTime" : 925846,
      "updatingStart" : "2025-07-08T06:36:38.014807Z",
      "updatingEnd" : "2025-07-08T06:36:39.124538Z",
      "totalSuspendedTime" : 0,
      "wasInterrupted" : false
    },
    "fileCount" : {
      "numberOfFileProviders" : 5,
      "numberOfScannedFiles" : 284,
      "numberOfFilesIndexedByInfrastructureExtensionsDuringScan" : 0,
      "numberOfFilesScheduledForIndexingAfterScan" : 1,
      "numberOfFilesIndexedByInfrastructureExtensionsDuringIndexingStage" : 0,
      "numberOfFilesIndexedWithLoadingContent" : 1
    },
    "totalStatsPerFileType" : [ {
      "fileType" : "UNKNOWN",
      "partOfTotalProcessingTime" : {
        "part" : 12001706,
        "total" : 12001706
      },
      "partOfTotalContentLoadingTime" : {
        "part" : 5357109,
        "total" : 5357109
      },
      "totalNumberOfFiles" : 1,
      "totalFilesSize" : 1939,
      "indexingSpeed" : {
        "totalBytes" : 1939,
        "totalTime" : 12001706
      },
      "biggestContributors" : [ {
        "providerName" : "Module 'doc' (doc)",
        "numberOfFiles" : 1,
        "totalFilesSize" : 1939,
        "partOfTotalProcessingTimeOfThisFileType" : {
          "part" : 12001706,
          "total" : 12001706
        }
      } ]
    } ],
    "totalStatsPerIndexer" : [ ],
    "scanningStatistics" : [ {
      "providerName" : "Module 'doc' (doc)",
      "numberOfScannedFiles" : 55,
      "numberOfSkippedFiles" : 0,
      "numberOfFilesForIndexing" : 1,
      "numberOfFilesFullyIndexedByInfrastructureExtensions" : 0,
      "filesFullyIndexedByInfrastructureExtensions" : [ ],
      "statusTime" : 698859070,
      "scanningTime" : 724748301,
      "timeProcessingUpToDateFiles" : 0,
      "timeUpdatingContentLessIndexes" : 578231,
      "timeIndexingWithoutContent" : 1980401,
      "roots" : [ ]
    }, {
      "providerName" : "Indexable set contributor 'com.intellij.javaee.ExternalResourcesRootsProvider@56d3092' (non-project)",
      "numberOfScannedFiles" : 229,
      "numberOfSkippedFiles" : 4,
      "numberOfFilesForIndexing" : 0,
      "numberOfFilesFullyIndexedByInfrastructureExtensions" : 0,
      "filesFullyIndexedByInfrastructureExtensions" : [ ],
      "statusTime" : 698046795,
      "scanningTime" : 705331877,
      "timeProcessingUpToDateFiles" : 0,
      "timeUpdatingContentLessIndexes" : 2541863,
      "timeIndexingWithoutContent" : 0,
      "roots" : [ ]
    }, {
      "providerName" : "Indexable set contributor 'com.intellij.javaee.ExternalResourcesRootsProvider@56d3092' (project)",
      "numberOfScannedFiles" : 0,
      "numberOfSkippedFiles" : 0,
      "numberOfFilesForIndexing" : 0,
      "numberOfFilesFullyIndexedByInfrastructureExtensions" : 0,
      "filesFullyIndexedByInfrastructureExtensions" : [ ],
      "statusTime" : 0,
      "scanningTime" : 0,
      "timeProcessingUpToDateFiles" : 0,
      "timeUpdatingContentLessIndexes" : 0,
      "timeIndexingWithoutContent" : 0,
      "roots" : [ ]
    }, {
      "providerName" : "Indexable set contributor 'Scratches & Consoles' (non-project)",
      "numberOfScannedFiles" : 0,
      "numberOfSkippedFiles" : 0,
      "numberOfFilesForIndexing" : 0,
      "numberOfFilesFullyIndexedByInfrastructureExtensions" : 0,
      "filesFullyIndexedByInfrastructureExtensions" : [ ],
      "statusTime" : 0,
      "scanningTime" : 0,
      "timeProcessingUpToDateFiles" : 0,
      "timeUpdatingContentLessIndexes" : 0,
      "timeIndexingWithoutContent" : 0,
      "roots" : [ ]
    }, {
      "providerName" : "Indexable set contributor 'Scratches & Consoles' (project)",
      "numberOfScannedFiles" : 0,
      "numberOfSkippedFiles" : 0,
      "numberOfFilesForIndexing" : 0,
      "numberOfFilesFullyIndexedByInfrastructureExtensions" : 0,
      "filesFullyIndexedByInfrastructureExtensions" : [ ],
      "statusTime" : 0,
      "scanningTime" : 0,
      "timeProcessingUpToDateFiles" : 0,
      "timeUpdatingContentLessIndexes" : 0,
      "timeIndexingWithoutContent" : 0,
      "roots" : [ ]
    } ],
    "fileProviderStatistics" : [ {
      "providerName" : "Module 'doc' (doc)",
      "totalNumberOfIndexedFiles" : 1,
      "totalNumberOfFilesFullyIndexedByExtensions" : 0,
      "totalIndexingVisibleTime" : 16341384,
      "contentLoadingVisibleTime" : 7294177,
      "numberOfTooLargeForIndexingFiles" : 0,
      "slowIndexedFiles" : [ ],
      "filesFullyIndexedByExtensions" : [ ],
      "isAppliedAllValuesSeparately" : true,
      "separateApplyingIndexesVisibleTime" : 925846
    } ],
    "visibleTimeToAllThreadTimeRatio" : 1.3615884275118888
  }
}